d2p_utils/__init__.py
d2p_utils/cli.py
d2p_utils/d2p_utils.py
d2p_utils/property_test_main.py
d2p_utils/property_test_treatment.py
d2p_utils-1.0.0.dist-info/AUTHORS.rst
d2p_utils-1.0.0.dist-info/LICENSE
d2p_utils-1.0.0.dist-info/METADATA
d2p_utils-1.0.0.dist-info/WHEEL
d2p_utils-1.0.0.dist-info/entry_points.txt
d2p_utils-1.0.0.dist-info/top_level.txt
d2p_utils-1.0.0.dist-info/RECORD
