Metadata-Version: 2.1
Name: d2p-utils
Version: 1.0.0
Summary: D2P Utils,resusable components
Home-page: https://github.com/audreyr/d2p_utils
Author: Karthik Challa
Author-email: audreyr@example.com
License: MIT license
Keywords: d2p_utils
Platform: UNKNOWN
Classifier: Development Status :: 2 - Pre-Alpha
Classifier: Intended Audience :: Developers
Classifier: License :: OSI Approved :: MIT License
Classifier: Natural Language :: English
Classifier: Programming Language :: Python :: 3
Classifier: Programming Language :: Python :: 3.5
Classifier: Programming Language :: Python :: 3.6
Classifier: Programming Language :: Python :: 3.7
Classifier: Programming Language :: Python :: 3.8
Requires-Python: >=3.5
